awherepy/__init__.py
awherepy/agronomics.py
awherepy/crops.py
awherepy/fields.py
awherepy/grids.py
awherepy/models.py
awherepy/plantings.py
awherepy/weather.py
awherepy-0.1.0.dist-info/LICENSE
awherepy-0.1.0.dist-info/METADATA
awherepy-0.1.0.dist-info/WHEEL
awherepy-0.1.0.dist-info/top_level.txt
awherepy-0.1.0.dist-info/RECORD
