Metadata-Version: 2.1
Name: awherepy
Version: 0.1.0
Summary: Python package built to work with weather and agriculture data in the aWhere API.
Home-page: https://github.com/calekochenour/awherepy
Maintainer: Cale Kochenour
Maintainer-email: cale.kochenour@alumni.psu.edu
License: UNKNOWN
Platform: UNKNOWN
Classifier: Intended Audience :: Developers
Classifier: License :: OSI Approved :: BSD License
Classifier: Programming Language :: Python
Classifier: Topic :: Software Development
Classifier: Operating System :: Microsoft :: Windows
Classifier: Operating System :: POSIX
Classifier: Operating System :: Unix
Classifier: Operating System :: MacOS
Requires-Dist: matplotlib
Requires-Dist: numpy
Requires-Dist: seaborn
Requires-Dist: geopandas
Requires-Dist: earthpy
Requires-Dist: shapely
Requires-Dist: rasterstats
Requires-Dist: descartes
Requires-Dist: rtree
